data_fetcher/__init__.py
data_fetcher/core.py
data_fetcher/extras.py
data_fetcher/global_request_context.py
data_fetcher/middleware.py
data_fetcher/shorthand_fetcher_classes.py
data_fetcher/util.py
django_data_fetcher-2.2.1.dist-info/METADATA
django_data_fetcher-2.2.1.dist-info/WHEEL
django_data_fetcher-2.2.1.dist-info/top_level.txt
django_data_fetcher-2.2.1.dist-info/RECORD
