Metadata-Version: 2.1
Name: django-data-fetcher
Version: 2.2.1
Home-page: https://github.com/AlexCLeduc/django-data-fetcher
Author: AlexCLeduc
Classifier: Programming Language :: Python :: 3
Classifier: License :: OSI Approved :: MIT License
Classifier: Operating System :: OS Independent
